flask_matomo2/__init__.py
flask_matomo2/core.py
flask_matomo2/py.typed
flask_matomo2/trackers.py
flask_matomo2-0.6.0.dist-info/METADATA
flask_matomo2-0.6.0.dist-info/WHEEL
flask_matomo2-0.6.0.dist-info/licenses/LICENSE
flask_matomo2-0.6.0.dist-info/RECORD
