Metadata-Version: 2.4
Name: flask-matomo2
Version: 0.6.0
Summary: Track requests to your Flask server with Matomo
Project-URL: Bug Tracker, https://github.com/spraakbanken/flask-matomo2/issues
Project-URL: homepage, https://spraakbanken.gu.se
Project-URL: repository, https://github.com/spraakbanken/flask-matomo2
Project-URL: documentation, http://flask-matomo2.readthedocs.io/
Author-email: Lucas Hild <contact@lucas-hild.de>, Språkbanken Text <sb-info@svenska.gu.se>, Kristoffer Andersson <kristoffer.andersson@gu.se>
Maintainer-email: Språkbanken Text <sb-info@svenska.gu.se>, Kristoffer Andersson <kristoffer.andersson@gu.se>
License: MIT
License-File: LICENSE
Classifier: Development Status :: 4 - Beta
Classifier: Environment :: Web Environment
Classifier: Intended Audience :: Developers
Classifier: License :: OSI Approved :: MIT License
Classifier: Operating System :: OS Independent
Classifier: Programming Language :: Python
Classifier: Programming Language :: Python :: 3.9
Classifier: Programming Language :: Python :: 3.10
Classifier: Programming Language :: Python :: 3.11
Classifier: Programming Language :: Python :: 3.12
Classifier: Programming Language :: Python :: 3.13
Classifier: Programming Language :: Python :: Implementation :: CPython
Classifier: Topic :: Internet :: WWW/HTTP :: Dynamic Content
Classifier: Topic :: Software Development :: Libraries :: Python Modules
Requires-Python: >=3.9
Requires-Dist: flask>=2.3
Requires-Dist: httpx>=0.24
Requires-Dist: werkzeug>=2.3.2
